randwalk/__init__.py
randwalk-1.1.data/scripts/randwalk
randwalk-1.1.data/scripts/randwalk-compare
randwalk-1.1.dist-info/LICENSE
randwalk-1.1.dist-info/METADATA
randwalk-1.1.dist-info/WHEEL
randwalk-1.1.dist-info/top_level.txt
randwalk-1.1.dist-info/RECORD
