Metadata-Version: 2.1
Name: randwalk
Version: 1.1
Summary: random walk agents on graph supporting several strategies
Home-page: https://github.com/h-ohsaki/randwalk.git
Author: Hiroyuki Ohsaki
Author-email: ohsaki@lsnl.jp
License: UNKNOWN
Platform: UNKNOWN
Classifier: Programming Language :: Python :: 3
Classifier: License :: OSI Approved :: GNU General Public License v3 or later (GPLv3+)
Classifier: Operating System :: POSIX
Requires-Dist: graph-tools
Requires-Dist: perlcompat
Requires-Dist: tbdump
